Metadata-Version: 1.1
Name: uw-atg-wx
Version: 0.0.3
Summary: A module to gather meteorologic data from the rooftop of the University of Washington Atmospheric Science department
Home-page: https://github.com/jsheedy/uw_atg_wx
Author: Joseph Sheedy
Author-email: joseph.sheedy@gmail.com
License: LICENSE.txt
Download-URL: https://github.com/jsheedy/uw_atg_wx/tarball/0.0.3
Keywords: weather
Platform: UNKNOWN
